{
    "version": "0.7.4",
    "description": "A query tool to join, analyse and transform data from multiple databases and file formats using SQL",
    "homepage": "https://github.com/cube2222/octosql",
    "license": "MPL-2.0",
    "architecture": {
        "64bit": {
            "url": "https://github.com/cube2222/octosql/releases/download/v0.7.4/octosql_0.7.4_windows_amd64.tar.gz",
            "hash": "c3fde68246becacd572fabc555316e38b972ebbeee4e989d1c41197663663452"
        }
    },
    "bin": "octosql.exe",
    "checkver": "github",
    "autoupdate": {
        "architecture": {
            "64bit": {
                "url": "https://github.com/cube2222/octosql/releases/download/v$version/octosql_$version_windows_amd64.tar.gz"
            }
        },
        "hash": {
            "url": "$baseurl/octosql_$version_checksums.txt"
        }
    }
}
